tembo_py/__init__.py
tembo_py/rag.py
tembo_py-0.3.0.dist-info/METADATA
tembo_py-0.3.0.dist-info/WHEEL
tembo_py-0.3.0.dist-info/RECORD
